{
    "SKOS_CONCEPT": [
        {
            "alt_label": "HAMA1-Anxious Mood",
            "definition": "Hamilton Anxiety Rating Scale - Anxious mood: worries, anticipation of the worst, fearful anticipation, irritability.",
            "identifier": "C102073",
            "notation": "HAMA101",
            "pref_label": "HAMA - Anxious Mood",
            "uri": "http://id.d4k.dk/dataset/cdisc/ct/v48/sdtm/C101819-C102073"
        },
        {
            "alt_label": "HAMA1-Tension",
            "definition": "Hamilton Anxiety Rating Scale - Tension: feelings of tension, fatigability, startle response, moved to tears easily, trembling, feelings of restlessness, inability to relax.",
            "identifier": "C102074",
            "notation": "HAMA102",
            "pref_label": "HAMA - Tension",
            "uri": "http://id.d4k.dk/dataset/cdisc/ct/v48/sdtm/C101819-C102074"
        },
        {
            "alt_label": "HAMA1-Fears",
            "definition": "Hamilton Anxiety Rating Scale - Fears: of dark, of strangers, of being left alone, of animals, of traffic, of crowds.",
            "identifier": "C102075",
            "notation": "HAMA103",
            "pref_label": "HAMA - Fears",
            "uri": "http://id.d4k.dk/dataset/cdisc/ct/v48/sdtm/C101819-C102075"
        },
        {
            "alt_label": "HAMA1-Insomnia",
            "definition": "Hamilton Anxiety Rating Scale - Insomnia: difficulty falling asleep, broken sleep, unsatisfying sleep and fatigue on waking, dreams, nightmares, night terrors.",
            "identifier": "C102076",
            "notation": "HAMA104",
            "pref_label": "HAMA - Insomnia",
            "uri": "http://id.d4k.dk/dataset/cdisc/ct/v48/sdtm/C101819-C102076"
        },
        {
            "alt_label": "HAMA1-Intellectual",
            "definition": "Hamilton Anxiety Rating Scale - Intellectual: difficulty in concentration, poor memory.",
            "identifier": "C102077",
            "notation": "HAMA105",
            "pref_label": "HAMA - Intellectual",
            "uri": "http://id.d4k.dk/dataset/cdisc/ct/v48/sdtm/C101819-C102077"
        },
        {
            "alt_label": "HAMA1-Depressed Mood",
            "definition": "Hamilton Anxiety Rating Scale - Depressed mood: loss of interest, lack of pleasure in hobbies, depression, early waking, diurnal swing.",
            "identifier": "C102078",
            "notation": "HAMA106",
            "pref_label": "HAMA - Depressed Mood",
            "uri": "http://id.d4k.dk/dataset/cdisc/ct/v48/sdtm/C101819-C102078"
        },
        {
            "alt_label": "HAMA1-Somatic (Muscular)",
            "definition": "Hamilton Anxiety Rating Scale - Somatic (muscular): pains and aches, twitching, stiffness, myoclonic jerks, grinding of teeth, unsteady voice, increased muscular tone.",
            "identifier": "C102079",
            "notation": "HAMA107",
            "pref_label": "HAMA - Somatic (Muscular)",
            "uri": "http://id.d4k.dk/dataset/cdisc/ct/v48/sdtm/C101819-C102079"
        },
        {
            "alt_label": "HAMA1-Somatic (Sensory)",
            "definition": "Hamilton Anxiety Rating Scale - Somatic (sensory): tinnitus, blurring of vision, hot and cold flushes, feelings of weakness, pricking sensation.",
            "identifier": "C102080",
            "notation": "HAMA108",
            "pref_label": "HAMA - Somatic (Sensory)",
            "uri": "http://id.d4k.dk/dataset/cdisc/ct/v48/sdtm/C101819-C102080"
        },
        {
            "alt_label": "HAMA1-Cardiovascular Symptoms",
            "definition": "Hamilton Anxiety Rating Scale - Cardiovascular symptoms: tachycardia, palpitations, pain in chest, throbbing of vessels, fainting feelings, missing beat.",
            "identifier": "C102081",
            "notation": "HAMA109",
            "pref_label": "HAMA - Cardiovascular Symptoms",
            "uri": "http://id.d4k.dk/dataset/cdisc/ct/v48/sdtm/C101819-C102081"
        },
        {
            "alt_label": "HAMA1-Respiratory Symptoms",
            "definition": "Hamilton Anxiety Rating Scale - Respiratory symptoms: pressure or constriction in chest, choking feelings, sighing, dyspnea.",
            "identifier": "C102082",
            "notation": "HAMA110",
            "pref_label": "HAMA - Respiratory Symptoms",
            "uri": "http://id.d4k.dk/dataset/cdisc/ct/v48/sdtm/C101819-C102082"
        },
        {
            "alt_label": "HAMA1-Gastrointestinal Symptoms",
            "definition": "Hamilton Anxiety Rating Scale - Gastrointestinal symptoms: difficulty swallowing, wind abdominal pain, burning sensations, abdominal fullness, nausea, vomiting, borborygmi, looseness of bowels, loss of weight, constipation.",
            "identifier": "C102083",
            "notation": "HAMA111",
            "pref_label": "HAMA - Gastrointestinal Symptoms",
            "uri": "http://id.d4k.dk/dataset/cdisc/ct/v48/sdtm/C101819-C102083"
        },
        {
            "alt_label": "HAMA1-Genitourinary Symptoms",
            "definition": "Hamilton Anxiety Rating Scale - Genitourinary symptoms: frequency of micturition, urgency of micturition, amenorrhea, menorrhagia, development of frigidity, premature ejaculation, loss of libido, impotence.",
            "identifier": "C102084",
            "notation": "HAMA112",
            "pref_label": "HAMA - Genitourinary Symptoms",
            "uri": "http://id.d4k.dk/dataset/cdisc/ct/v48/sdtm/C101819-C102084"
        },
        {
            "alt_label": "HAMA1-Autonomic Symptoms",
            "definition": "Hamilton Anxiety Rating Scale - Autonomic symptoms: dry mouth, flushing, pallor, tendency to sweat, giddiness, tension, headache, raising of hair.",
            "identifier": "C102085",
            "notation": "HAMA113",
            "pref_label": "HAMA - Autonomic Symptoms",
            "uri": "http://id.d4k.dk/dataset/cdisc/ct/v48/sdtm/C101819-C102085"
        },
        {
            "alt_label": "HAMA1-Behavior at Interview",
            "definition": "Hamilton Anxiety Rating Scale - Behavior at interview: fidgeting, restlessness or pacing, tremor of hands, furrowed brow, strained face, sighing or rapid respiration, facial pallor, swallowing, etc.",
            "identifier": "C102086",
            "notation": "HAMA114",
            "pref_label": "HAMA - Behavior at Interview",
            "uri": "http://id.d4k.dk/dataset/cdisc/ct/v48/sdtm/C101819-C102086"
        },
        {
            "alt_label": "HAMA1-Total Score",
            "definition": "Hamilton Anxiety Rating Scale - Total score.",
            "identifier": "C155646",
            "notation": "HAMA115",
            "pref_label": "HAMA - Total Score",
            "uri": "http://id.d4k.dk/dataset/cdisc/ct/v48/sdtm/C101819-C155646"
        }
    ]
}