{
    "SKOS_CONCEPT": [
        {
            "alt_label": "",
            "definition": "An individual that came into contact with a source of Tuberculosis.",
            "identifier": "C102714",
            "notation": "CONTACT WITH TUBERCULOSIS SOURCE",
            "pref_label": "Subject in Contact With Tuberculosis Source",
            "uri": "http://id.d4k.dk/dataset/cdisc/ct/v48/sdtm/C102587-C102714"
        },
        {
            "alt_label": "",
            "definition": "An individual who is presently or not long ago worked or offered to assist without pay at a temporary housing facility for persons without a stable or permanent residence.",
            "identifier": "C102613",
            "notation": "CURRENT OR RECENT EMPLOYEE OR VOLUNTEER IN HOMELESS SHELTER",
            "pref_label": "Current or Recent Employee or Volunteer in Homeless Shelter",
            "uri": "http://id.d4k.dk/dataset/cdisc/ct/v48/sdtm/C102587-C102613"
        },
        {
            "alt_label": "",
            "definition": "An individual who is presently or not long ago worked or offered to assist without pay at an institution where persons are confined for punishment and to protect the public.",
            "identifier": "C102614",
            "notation": "CURRENT OR RECENT EMPLOYEE OR VOLUNTEER IN JAIL OR PRISON",
            "pref_label": "Current or Recent Employee or Volunteer in Jail or Prison",
            "uri": "http://id.d4k.dk/dataset/cdisc/ct/v48/sdtm/C102587-C102614"
        },
        {
            "alt_label": "",
            "definition": "An individual who is presently or not long ago worked or offered to assist without pay at a residential health care facility for persons with chronic illness or disability.",
            "identifier": "C102615",
            "notation": "CURRENT OR RECENT EMPLOYEE OR VOLUNTEER IN NURSING HOME",
            "pref_label": "Current or Recent Employee or Volunteer in Nursing Home",
            "uri": "http://id.d4k.dk/dataset/cdisc/ct/v48/sdtm/C102587-C102615"
        },
        {
            "alt_label": "",
            "definition": "An individual without a stable or permanent residence within the last 365 days.",
            "identifier": "C102645",
            "notation": "HOMELESS DURING PAST YEAR",
            "pref_label": "Homeless During Past Year",
            "uri": "http://id.d4k.dk/dataset/cdisc/ct/v48/sdtm/C102587-C102645"
        },
        {
            "alt_label": "",
            "definition": "An individual that has migrated from a country with a high occurrence of tuberculosis.",
            "identifier": "C102648",
            "notation": "IMMIGRANT FROM HIGH TUBERCULOSIS PREVALENT AREA",
            "pref_label": "Immigrant From High Tuberculosis Prevalent Area",
            "uri": "http://id.d4k.dk/dataset/cdisc/ct/v48/sdtm/C102587-C102648"
        },
        {
            "alt_label": "",
            "definition": "The state of being confined to jail or prison.",
            "identifier": "C85521",
            "notation": "INCARCERATION",
            "pref_label": "Incarceration",
            "uri": "http://id.d4k.dk/dataset/cdisc/ct/v48/sdtm/C102587-C85521"
        },
        {
            "alt_label": "",
            "definition": "An individual that resided in a camp for those displaced from their homeland.",
            "identifier": "C102657",
            "notation": "LIVED IN REFUGEE CAMP",
            "pref_label": "Lived in Refugee Camp",
            "uri": "http://id.d4k.dk/dataset/cdisc/ct/v48/sdtm/C102587-C102657"
        },
        {
            "alt_label": "",
            "definition": "An individual that lives at a healthcare facility that provides rehabilitative, restorative, and/or ongoing skilled nursing care to patients or residents in need of assistance with activities of daily living.",
            "identifier": "C102660",
            "notation": "LONG-TERM FACILITY RESIDENT",
            "pref_label": "Long-term Facility Resident",
            "uri": "http://id.d4k.dk/dataset/cdisc/ct/v48/sdtm/C102587-C102660"
        },
        {
            "alt_label": "",
            "definition": "An individual who moves from one location to another location within or outside of their homeland for work.",
            "identifier": "C102670",
            "notation": "MIGRATORY WORKER",
            "pref_label": "Migratory Worker",
            "uri": "http://id.d4k.dk/dataset/cdisc/ct/v48/sdtm/C102587-C102670"
        },
        {
            "alt_label": "",
            "definition": "An individual that has fled a country for their own safety which has a high occurrence of tuberculosis.",
            "identifier": "C102705",
            "notation": "REFUGEE FROM HIGH TUBERCULOSIS PREVALENT AREA",
            "pref_label": "Refugee From High Tuberculosis Prevalent Area",
            "uri": "http://id.d4k.dk/dataset/cdisc/ct/v48/sdtm/C102587-C102705"
        },
        {
            "alt_label": "",
            "definition": "Entry into one or more of the 22 countries that have a relatively high prevalence of tuberculosis cases.",
            "identifier": "C102719",
            "notation": "TRAVEL TO HIGH BURDEN COUNTRY",
            "pref_label": "Travel To High Burden Tuberculosis Country",
            "uri": "http://id.d4k.dk/dataset/cdisc/ct/v48/sdtm/C102587-C102719"
        },
        {
            "alt_label": "",
            "definition": "The state of not having a job.",
            "identifier": "C75563",
            "notation": "UNEMPLOYMENT",
            "pref_label": "Unemployed",
            "uri": "http://id.d4k.dk/dataset/cdisc/ct/v48/sdtm/C102587-C75563"
        }
    ]
}