{
    "SKOS_CONCEPT": [
        {
            "alt_label": "EXACT1-Chest Feel Congested",
            "definition": "Exacerbations of Chronic Pulmonary Disease Tool Patient-Reported Outcome - Did your chest feel congested today?",
            "identifier": "C123669",
            "notation": "EXACT101",
            "pref_label": "EXACT - Chest Feel Congested",
            "uri": "http://id.d4k.dk/dataset/cdisc/ct/v48/sdtm/C123653-C123669"
        },
        {
            "alt_label": "EXACT1-How Often Cough",
            "definition": "Exacerbations of Chronic Pulmonary Disease Tool Patient-Reported Outcome - How often did you cough today?",
            "identifier": "C123670",
            "notation": "EXACT102",
            "pref_label": "EXACT - How Often Cough Today",
            "uri": "http://id.d4k.dk/dataset/cdisc/ct/v48/sdtm/C123653-C123670"
        },
        {
            "alt_label": "EXACT1-Bring Up Mucus When Coughing",
            "definition": "Exacerbations of Chronic Pulmonary Disease Tool Patient-Reported Outcome - How much mucus (phlegm) did you bring up when coughing today?",
            "identifier": "C123671",
            "notation": "EXACT103",
            "pref_label": "EXACT - Bring Up Mucus When Coughing",
            "uri": "http://id.d4k.dk/dataset/cdisc/ct/v48/sdtm/C123653-C123671"
        },
        {
            "alt_label": "EXACT1-Difficult to Bring Up Mucus",
            "definition": "Exacerbations of Chronic Pulmonary Disease Tool Patient-Reported Outcome - How difficult was it to bring up mucus (phlegm) today?",
            "identifier": "C123672",
            "notation": "EXACT104",
            "pref_label": "EXACT - Difficult to Bring Up Mucus",
            "uri": "http://id.d4k.dk/dataset/cdisc/ct/v48/sdtm/C123653-C123672"
        },
        {
            "alt_label": "EXACT1-Chest Discomfort",
            "definition": "Exacerbations of Chronic Pulmonary Disease Tool Patient-Reported Outcome - Did you have chest discomfort today?",
            "identifier": "C123673",
            "notation": "EXACT105",
            "pref_label": "EXACT - Have Chest Discomfort",
            "uri": "http://id.d4k.dk/dataset/cdisc/ct/v48/sdtm/C123653-C123673"
        },
        {
            "alt_label": "EXACT1-Chest Feel Tight",
            "definition": "Exacerbations of Chronic Pulmonary Disease Tool Patient-Reported Outcome - Did your chest feel tight today?",
            "identifier": "C123674",
            "notation": "EXACT106",
            "pref_label": "EXACT - Chest Feel Tight",
            "uri": "http://id.d4k.dk/dataset/cdisc/ct/v48/sdtm/C123653-C123674"
        },
        {
            "alt_label": "EXACT1-Breathless",
            "definition": "Exacerbations of Chronic Pulmonary Disease Tool Patient-Reported Outcome - Were you breathless today?",
            "identifier": "C123675",
            "notation": "EXACT107",
            "pref_label": "EXACT - Were You Breathless",
            "uri": "http://id.d4k.dk/dataset/cdisc/ct/v48/sdtm/C123653-C123675"
        },
        {
            "alt_label": "EXACT1-Describe How Breathless",
            "definition": "Exacerbations of Chronic Pulmonary Disease Tool Patient-Reported Outcome - Describe how breathless you were today.",
            "identifier": "C123676",
            "notation": "EXACT108",
            "pref_label": "EXACT - Describe How Breathless",
            "uri": "http://id.d4k.dk/dataset/cdisc/ct/v48/sdtm/C123653-C123676"
        },
        {
            "alt_label": "EXACT1-Short Breath Personal Care",
            "definition": "Exacerbations of Chronic Pulmonary Disease Tool Patient-Reported Outcome - Were you short of breath today when performing your usual personal care activities like washing or dressing?",
            "identifier": "C123677",
            "notation": "EXACT109",
            "pref_label": "EXACT - Short of Breath When Performing Usual Personal Care",
            "uri": "http://id.d4k.dk/dataset/cdisc/ct/v48/sdtm/C123653-C123677"
        },
        {
            "alt_label": "EXACT1-Short Breath Indoor Activities",
            "definition": "Exacerbations of Chronic Pulmonary Disease Tool Patient-Reported Outcome - Were you short of breath today when performing your usual indoor activities like cleaning or household work?",
            "identifier": "C123678",
            "notation": "EXACT110",
            "pref_label": "EXACT - Short of Breath When Performing Usual Indoor Activities",
            "uri": "http://id.d4k.dk/dataset/cdisc/ct/v48/sdtm/C123653-C123678"
        },
        {
            "alt_label": "EXACT1-Short Breath Outside Activities",
            "definition": "Exacerbations of Chronic Pulmonary Disease Tool Patient-Reported Outcome - Were you short of breath today when performing your usual activities outside the home such as yard work or errands?",
            "identifier": "C123679",
            "notation": "EXACT111",
            "pref_label": "EXACT - Short of Breath When Performing Usual Activities Outside",
            "uri": "http://id.d4k.dk/dataset/cdisc/ct/v48/sdtm/C123653-C123679"
        },
        {
            "alt_label": "EXACT1-Tired or Weak",
            "definition": "Exacerbations of Chronic Pulmonary Disease Tool Patient-Reported Outcome - Were you tired or weak today?",
            "identifier": "C123680",
            "notation": "EXACT112",
            "pref_label": "EXACT - Tired or Weak",
            "uri": "http://id.d4k.dk/dataset/cdisc/ct/v48/sdtm/C123653-C123680"
        },
        {
            "alt_label": "EXACT1-Night Sleep Disturbed",
            "definition": "Exacerbations of Chronic Pulmonary Disease Tool Patient-Reported Outcome - Last night, was your sleep disturbed?",
            "identifier": "C123681",
            "notation": "EXACT113",
            "pref_label": "EXACT - Night Sleep Disturbed",
            "uri": "http://id.d4k.dk/dataset/cdisc/ct/v48/sdtm/C123653-C123681"
        },
        {
            "alt_label": "EXACT1-Worried About Lung Problems",
            "definition": "Exacerbations of Chronic Pulmonary Disease Tool Patient-Reported Outcome - How scared or worried were you about your lung problems today?",
            "identifier": "C123682",
            "notation": "EXACT114",
            "pref_label": "EXACT - Worried About Lung Problems",
            "uri": "http://id.d4k.dk/dataset/cdisc/ct/v48/sdtm/C123653-C123682"
        },
        {
            "alt_label": "EXACT1-Breathlessness Raw Score",
            "definition": "Exacerbations of Chronic Pulmonary Disease Tool Patient-Reported Outcome - Breathlessness raw score.",
            "identifier": "C177803",
            "notation": "EXACT115",
            "pref_label": "EXACT - Breathlessness Raw Score",
            "uri": "http://id.d4k.dk/dataset/cdisc/ct/v48/sdtm/C123653-C177803"
        },
        {
            "alt_label": "EXACT1-Cough & Sputum Raw Score",
            "definition": "Exacerbations of Chronic Pulmonary Disease Tool Patient-Reported Outcome - Cough & sputum raw score.",
            "identifier": "C177804",
            "notation": "EXACT116",
            "pref_label": "EXACT - Cough & Sputum Raw Score",
            "uri": "http://id.d4k.dk/dataset/cdisc/ct/v48/sdtm/C123653-C177804"
        },
        {
            "alt_label": "EXACT1-Chest Symptoms Raw Score",
            "definition": "Exacerbations of Chronic Pulmonary Disease Tool Patient-Reported Outcome - Chest symptoms raw score.",
            "identifier": "C177805",
            "notation": "EXACT117",
            "pref_label": "EXACT - Chest Symptoms Raw Score",
            "uri": "http://id.d4k.dk/dataset/cdisc/ct/v48/sdtm/C123653-C177805"
        },
        {
            "alt_label": "EXACT1-EXACT Total Raw Score",
            "definition": "Exacerbations of Chronic Pulmonary Disease Tool Patient-Reported Outcome - Exact total raw score.",
            "identifier": "C177806",
            "notation": "EXACT118",
            "pref_label": "EXACT - EXACT Total Raw Score",
            "uri": "http://id.d4k.dk/dataset/cdisc/ct/v48/sdtm/C123653-C177806"
        },
        {
            "alt_label": "EXACT1-Breathlessness Domain Score",
            "definition": "Exacerbations of Chronic Pulmonary Disease Tool Patient-Reported Outcome - Breathlessness domain score.",
            "identifier": "C177807",
            "notation": "EXACT119",
            "pref_label": "EXACT - Breathlessness Domain Score",
            "uri": "http://id.d4k.dk/dataset/cdisc/ct/v48/sdtm/C123653-C177807"
        },
        {
            "alt_label": "EXACT1-Cough & Sputum Domain Score",
            "definition": "Exacerbations of Chronic Pulmonary Disease Tool Patient-Reported Outcome - Cough & sputum domain score.",
            "identifier": "C177808",
            "notation": "EXACT120",
            "pref_label": "EXACT - Cough & Sputum Domain Score",
            "uri": "http://id.d4k.dk/dataset/cdisc/ct/v48/sdtm/C123653-C177808"
        },
        {
            "alt_label": "EXACT1-Chest Symptoms Domain Score",
            "definition": "Exacerbations of Chronic Pulmonary Disease Tool Patient-Reported Outcome - Chest symptoms domain score.",
            "identifier": "C177809",
            "notation": "EXACT121",
            "pref_label": "EXACT - Chest Symptoms Domain Score",
            "uri": "http://id.d4k.dk/dataset/cdisc/ct/v48/sdtm/C123653-C177809"
        },
        {
            "alt_label": "EXACT1-EXACT Total Score",
            "definition": "Exacerbations of Chronic Pulmonary Disease Tool Patient-Reported Outcome - Exact total domain score.",
            "identifier": "C177810",
            "notation": "EXACT122",
            "pref_label": "EXACT - EXACT Total Score",
            "uri": "http://id.d4k.dk/dataset/cdisc/ct/v48/sdtm/C123653-C177810"
        }
    ]
}