{
    "SKOS_CONCEPT": [
        {
            "alt_label": "ADL02-Clear Dishes Usual Performance",
            "definition": "Alzheimer's Disease Cooperative Study-Activities of Daily Living Inventory, Severe Dementia Version - If yes, which best describes how {S} usually performed.",
            "identifier": "C106994",
            "notation": "ADL02-Clear Dishes Usual Performance",
            "pref_label": "ADCS-ADL Severe Dementia - Description of Usual Performance of Clearing Dishes",
            "uri": "http://id.d4k.dk/dataset/cdisc/ct/v48/sdtm/C106652-C106994"
        },
        {
            "alt_label": "ADL02-Clear Dishes",
            "definition": "Alzheimer's Disease Cooperative Study-Activities of Daily Living Inventory, Severe Dementia Version - Did {S} clear the dishes from the table after a meal or snack?",
            "identifier": "C106993",
            "notation": "ADL02-Clear Dishes",
            "pref_label": "ADCS-ADL Severe Dementia - Clear Dishes After Meal or Snack",
            "uri": "http://id.d4k.dk/dataset/cdisc/ct/v48/sdtm/C106652-C106993"
        },
        {
            "alt_label": "ADL02-Dispose Garbage Usual Performance",
            "definition": "Alzheimer's Disease Cooperative Study-Activities of Daily Living Inventory, Severe Dementia Version - If yes, which best describes how {S} usually performed.",
            "identifier": "C107000",
            "notation": "ADL02-Dispose Garbage Usual Performance",
            "pref_label": "ADCS-ADL Severe Dementia - Description of Usual Performance of Garbage Disposal",
            "uri": "http://id.d4k.dk/dataset/cdisc/ct/v48/sdtm/C106652-C107000"
        },
        {
            "alt_label": "ADL02-Dispose of Garbage",
            "definition": "Alzheimer's Disease Cooperative Study-Activities of Daily Living Inventory, Severe Dementia Version - In the past 4 weeks, did {S} dispose of garbage or litter in an appropriate place or container at home?",
            "identifier": "C106999",
            "notation": "ADL02-Dispose of Garbage",
            "pref_label": "ADCS-ADL Severe Dementia - Dispose of Garbage in Appropriate Place at Home",
            "uri": "http://id.d4k.dk/dataset/cdisc/ct/v48/sdtm/C106652-C106999"
        },
        {
            "alt_label": "ADL02-Find Belongings Usual Performance",
            "definition": "Alzheimer's Disease Cooperative Study-Activities of Daily Living Inventory, Severe Dementia Version - If yes, which best describes how {S} usually performed.",
            "identifier": "C106996",
            "notation": "ADL02-Find Belongings Usual Performance",
            "pref_label": "ADCS-ADL Severe Dementia - Description of Usual Performance of Finding Personal Belonging at Home",
            "uri": "http://id.d4k.dk/dataset/cdisc/ct/v48/sdtm/C106652-C106996"
        },
        {
            "alt_label": "ADL02-Find Belongings",
            "definition": "Alzheimer's Disease Cooperative Study-Activities of Daily Living Inventory, Severe Dementia Version - In the past 4 weeks, did {S} usually manage to find his/her personal belongings at home?",
            "identifier": "C106995",
            "notation": "ADL02-Find Belongings",
            "pref_label": "ADCS-ADL Severe Dementia - Find Personal Belongings at Home",
            "uri": "http://id.d4k.dk/dataset/cdisc/ct/v48/sdtm/C106652-C106995"
        },
        {
            "alt_label": "ADL02-Get Around Optimal Performance",
            "definition": "Alzheimer's Disease Cooperative Study-Activities of Daily Living Inventory, Severe Dementia Version - If yes, which best describes {S} optimal performance.",
            "identifier": "C107002",
            "notation": "ADL02-Get Around Optimal Performance",
            "pref_label": "ADCS-ADL Severe Dementia - Description of Optimal Performance of Getting Around Outside of Home",
            "uri": "http://id.d4k.dk/dataset/cdisc/ct/v48/sdtm/C106652-C107002"
        },
        {
            "alt_label": "ADL02-Get Around Outside Home",
            "definition": "Alzheimer's Disease Cooperative Study-Activities of Daily Living Inventory, Severe Dementia Version - In the past 4 weeks, did {S} get around (or travel) outside of his/her home?",
            "identifier": "C107001",
            "notation": "ADL02-Get Around Outside Home",
            "pref_label": "ADCS-ADL Severe Dementia - Get Around Outside Home",
            "uri": "http://id.d4k.dk/dataset/cdisc/ct/v48/sdtm/C106652-C107001"
        },
        {
            "alt_label": "ADL02-Highest Telephone Use Performance",
            "definition": "Alzheimer's Disease Cooperative Study-Activities of Daily Living Inventory, Severe Dementia Version - If yes, which best describes {S} highest level of performance.",
            "identifier": "C106986",
            "notation": "ADL02-Highest Telephone Use Performance",
            "pref_label": "ADCS-ADL Severe Dementia - Description of Highest Performance of Telephone Use",
            "uri": "http://id.d4k.dk/dataset/cdisc/ct/v48/sdtm/C106652-C106986"
        },
        {
            "alt_label": "ADL02-Left at Home for 1 Hour or Longer",
            "definition": "Alzheimer's Disease Cooperative Study-Activities of Daily Living Inventory, Severe Dementia Version - Was {S} left: at home for an hour or longer during the day?",
            "identifier": "C107005",
            "notation": "ADL02-Left at Home for 1 Hour or Longer",
            "pref_label": "ADCS-ADL Severe Dementia - Alone at Home for One Hour or Longer",
            "uri": "http://id.d4k.dk/dataset/cdisc/ct/v48/sdtm/C106652-C107005"
        },
        {
            "alt_label": "ADL02-Left at Home for Less Than 1 Hour",
            "definition": "Alzheimer's Disease Cooperative Study-Activities of Daily Living Inventory, Severe Dementia Version - Was {S} left: at home for less than 1 hour during the day?",
            "identifier": "C107006",
            "notation": "ADL02-Left at Home for Less Than 1 Hour",
            "pref_label": "ADCS-ADL Severe Dementia - Alone at Home for Less Than One Hour",
            "uri": "http://id.d4k.dk/dataset/cdisc/ct/v48/sdtm/C106652-C107006"
        },
        {
            "alt_label": "ADL02-Left Away From Home",
            "definition": "Alzheimer's Disease Cooperative Study-Activities of Daily Living Inventory, Severe Dementia Version - Was {S} left: away from home for 15 minutes or longer, during the day?",
            "identifier": "C107004",
            "notation": "ADL02-Left Away From Home",
            "pref_label": "ADCS-ADL Severe Dementia - Alone Away From Home for Fifteen Minutes or Longer",
            "uri": "http://id.d4k.dk/dataset/cdisc/ct/v48/sdtm/C106652-C107004"
        },
        {
            "alt_label": "ADL02-Left On His/Her Own",
            "definition": "Alzheimer's Disease Cooperative Study-Activities of Daily Living Inventory, Severe Dementia Version - In the past 4 weeks, was {S} ever left on his/her own?",
            "identifier": "C107003",
            "notation": "ADL02-Left On His/Her Own",
            "pref_label": "ADCS-ADL Severe Dementia - Subject Left on Their Own",
            "uri": "http://id.d4k.dk/dataset/cdisc/ct/v48/sdtm/C106652-C107003"
        },
        {
            "alt_label": "ADL02-Obtain Beverage Highest Perform",
            "definition": "Alzheimer's Disease Cooperative Study-Activities of Daily Living Inventory, Severe Dementia Version - If yes, which best describes {S} highest level of performance.",
            "identifier": "C106998",
            "notation": "ADL02-Obtain Beverage Highest Perform",
            "pref_label": "ADCS-ADL Severe Dementia - Description of Highest Performance of Obtaining Beverage",
            "uri": "http://id.d4k.dk/dataset/cdisc/ct/v48/sdtm/C106652-C106998"
        },
        {
            "alt_label": "ADL02-Obtain Beverage",
            "definition": "Alzheimer's Disease Cooperative Study-Activities of Daily Living Inventory, Severe Dementia Version - In the past 4 weeks, did {S} obtain a hot or cold beverage for him/herself?",
            "identifier": "C106997",
            "notation": "ADL02-Obtain Beverage",
            "pref_label": "ADCS-ADL Severe Dementia - Obtain Beverage for Self",
            "uri": "http://id.d4k.dk/dataset/cdisc/ct/v48/sdtm/C106652-C106997"
        },
        {
            "alt_label": "ADL02-Optimal Grooming Performance",
            "definition": "Alzheimer's Disease Cooperative Study-Activities of Daily Living Inventory, Severe Dementia Version - Regarding grooming, in the past 4 weeks, which best describes {S} optimal performance?",
            "identifier": "C106983",
            "notation": "ADL02-Optimal Grooming Performance",
            "pref_label": "ADCS-ADL Severe Dementia - Description of Optimal Performance of Grooming",
            "uri": "http://id.d4k.dk/dataset/cdisc/ct/v48/sdtm/C106652-C106983"
        },
        {
            "alt_label": "ADL02-Optimal Walking Performance",
            "definition": "Alzheimer's Disease Cooperative Study-Activities of Daily Living Inventory, Severe Dementia Version - Regarding walking (or getting around in a wheelchair) in the past 4 weeks, which best describes {S} optimal performance?",
            "identifier": "C106980",
            "notation": "ADL02-Optimal Walking Performance",
            "pref_label": "ADCS-ADL Severe Dementia - Description of Optimal Performance of Walking",
            "uri": "http://id.d4k.dk/dataset/cdisc/ct/v48/sdtm/C106652-C106980"
        },
        {
            "alt_label": "ADL02-Pay Attention to Conversation",
            "definition": "Alzheimer's Disease Cooperative Study-Activities of Daily Living Inventory, Severe Dementia Version - In the past 4 weeks, did {S} ever appear to pay attention to conversation or small talk for at least 5 minutes?",
            "identifier": "C106991",
            "notation": "ADL02-Pay Attention to Conversation",
            "pref_label": "ADCS-ADL Severe Dementia - Pay Attention to Conversation",
            "uri": "http://id.d4k.dk/dataset/cdisc/ct/v48/sdtm/C106652-C106991"
        },
        {
            "alt_label": "ADL02-Run Water Faucet to Wash",
            "definition": "Alzheimer's Disease Cooperative Study-Activities of Daily Living Inventory, Severe Dementia Version - In the past 4 weeks, did {S} usually run water from a faucet to wash {S} hands or face without help?",
            "identifier": "C107007",
            "notation": "ADL02-Run Water Faucet to Wash",
            "pref_label": "ADCS-ADL Severe Dementia - Turn On Faucet to Wash Without Help",
            "uri": "http://id.d4k.dk/dataset/cdisc/ct/v48/sdtm/C106652-C107007"
        },
        {
            "alt_label": "ADL02-Select Television Program",
            "definition": "Alzheimer's Disease Cooperative Study-Activities of Daily Living Inventory, Severe Dementia Version - Did {S} usually select or ask for different programs or {S} favorite show?",
            "identifier": "C106988",
            "notation": "ADL02-Select Television Program",
            "pref_label": "ADCS-ADL Severe Dementia - Select or Ask for Television Program",
            "uri": "http://id.d4k.dk/dataset/cdisc/ct/v48/sdtm/C106652-C106988"
        },
        {
            "alt_label": "ADL02-Sum 1 to 5",
            "definition": "Alzheimer's Disease Cooperative Study-Activities of Daily Living Inventory, Severe Dementia Version - Sum of Items 1-5.",
            "identifier": "C107011",
            "notation": "ADL02-Sum 1 to 5",
            "pref_label": "ADCS-ADL Severe Dementia - Sum of Items 1-5",
            "uri": "http://id.d4k.dk/dataset/cdisc/ct/v48/sdtm/C106652-C107011"
        },
        {
            "alt_label": "ADL02-Sum 13 to 15",
            "definition": "Alzheimer's Disease Cooperative Study-Activities of Daily Living Inventory, Severe Dementia Version - Sum of Items 13-15.",
            "identifier": "C107014",
            "notation": "ADL02-Sum 13 to 15",
            "pref_label": "ADCS-ADL Severe Dementia - Sum of Items 13-15",
            "uri": "http://id.d4k.dk/dataset/cdisc/ct/v48/sdtm/C106652-C107014"
        },
        {
            "alt_label": "ADL02-Sum 16 to 19",
            "definition": "Alzheimer's Disease Cooperative Study-Activities of Daily Living Inventory, Severe Dementia Version - Sum of Items 16-19.",
            "identifier": "C107015",
            "notation": "ADL02-Sum 16 to 19",
            "pref_label": "ADCS-ADL Severe Dementia - Sum of Items 16-19",
            "uri": "http://id.d4k.dk/dataset/cdisc/ct/v48/sdtm/C106652-C107015"
        },
        {
            "alt_label": "ADL02-Sum 6 to 8",
            "definition": "Alzheimer's Disease Cooperative Study-Activities of Daily Living Inventory, Severe Dementia Version - Sum of Items 6-8.",
            "identifier": "C107012",
            "notation": "ADL02-Sum 6 to 8",
            "pref_label": "ADCS-ADL Severe Dementia - Sum of Items 6-8",
            "uri": "http://id.d4k.dk/dataset/cdisc/ct/v48/sdtm/C106652-C107012"
        },
        {
            "alt_label": "ADL02-Sum 9 to 12",
            "definition": "Alzheimer's Disease Cooperative Study-Activities of Daily Living Inventory, Severe Dementia Version - Sum of Items 9-12.",
            "identifier": "C107013",
            "notation": "ADL02-Sum 9 to 12",
            "pref_label": "ADCS-ADL Severe Dementia - Sum of Items 9-12",
            "uri": "http://id.d4k.dk/dataset/cdisc/ct/v48/sdtm/C106652-C107013"
        },
        {
            "alt_label": "ADL02-Talk About TV Content While Watch",
            "definition": "Alzheimer's Disease Cooperative Study-Activities of Daily Living Inventory, Severe Dementia Version - Did {S} usually talk about the content of a program while watching it?",
            "identifier": "C106989",
            "notation": "ADL02-Talk About TV Content While Watch",
            "pref_label": "ADCS-ADL Severe Dementia - Talk About TV Content While Watching",
            "uri": "http://id.d4k.dk/dataset/cdisc/ct/v48/sdtm/C106652-C106989"
        },
        {
            "alt_label": "ADL02-Talk About TV Content Within a Day",
            "definition": "Alzheimer's Disease Cooperative Study-Activities of Daily Living Inventory, Severe Dementia Version - Did {S} talk about the content of a program within a day (24 hours) after watching it?",
            "identifier": "C106990",
            "notation": "ADL02-Talk About TV Content Within a Day",
            "pref_label": "ADCS-ADL Severe Dementia - Talk About TV Content Within a Day After Watching",
            "uri": "http://id.d4k.dk/dataset/cdisc/ct/v48/sdtm/C106652-C106990"
        },
        {
            "alt_label": "ADL02-Total ADCS-ADL Score",
            "definition": "Alzheimer's Disease Cooperative Study-Activities of Daily Living Inventory, Severe Dementia Version - Total Score.",
            "identifier": "C107016",
            "notation": "ADL02-Total ADCS-ADL Score",
            "pref_label": "ADCS-ADL Severe Dementia - Total Score",
            "uri": "http://id.d4k.dk/dataset/cdisc/ct/v48/sdtm/C106652-C107016"
        },
        {
            "alt_label": "ADL02-Turn Off Faucet",
            "definition": "Alzheimer's Disease Cooperative Study-Activities of Daily Living Inventory, Severe Dementia Version - In the past 4 weeks, did {S} usually turn off the faucet after finishing running water without help?",
            "identifier": "C107008",
            "notation": "ADL02-Turn Off Faucet",
            "pref_label": "ADCS-ADL Severe Dementia - Turn Off Faucet After Wash Without Help",
            "uri": "http://id.d4k.dk/dataset/cdisc/ct/v48/sdtm/C106652-C107008"
        },
        {
            "alt_label": "ADL02-Turn Off Light",
            "definition": "Alzheimer's Disease Cooperative Study-Activities of Daily Living Inventory, Severe Dementia Version - In the past 4 weeks, did {S} usually turn off lights without help when leaving a room or going to sleep?",
            "identifier": "C107010",
            "notation": "ADL02-Turn Off Light",
            "pref_label": "ADCS-ADL Severe Dementia - Turn Off Light Without Help Leaving Room",
            "uri": "http://id.d4k.dk/dataset/cdisc/ct/v48/sdtm/C106652-C107010"
        },
        {
            "alt_label": "ADL02-Turn On Light",
            "definition": "Alzheimer's Disease Cooperative Study-Activities of Daily Living Inventory, Severe Dementia Version - In the past 4 weeks, did {S} usually turn on a light without help when entering a dark room or area?",
            "identifier": "C107009",
            "notation": "ADL02-Turn On Light",
            "pref_label": "ADCS-ADL Severe Dementia - Turn On Light Without Help Entering Room",
            "uri": "http://id.d4k.dk/dataset/cdisc/ct/v48/sdtm/C106652-C107009"
        },
        {
            "alt_label": "ADL02-Use a Telephone",
            "definition": "Alzheimer's Disease Cooperative Study-Activities of Daily Living Inventory, Severe Dementia Version - In the past 4 weeks, did {S} use a telephone?",
            "identifier": "C106985",
            "notation": "ADL02-Use a Telephone",
            "pref_label": "ADCS-ADL Severe Dementia - Use a Telephone",
            "uri": "http://id.d4k.dk/dataset/cdisc/ct/v48/sdtm/C106652-C106985"
        },
        {
            "alt_label": "ADL02-Usual Bathing Performance",
            "definition": "Alzheimer's Disease Cooperative Study-Activities of Daily Living Inventory, Severe Dementia Version - Regarding bathing, in the past 4 weeks, which best describes {S} usual performance?",
            "identifier": "C106982",
            "notation": "ADL02-Usual Bathing Performance",
            "pref_label": "ADCS-ADL Severe Dementia - Description of Usual Performance of Bathing",
            "uri": "http://id.d4k.dk/dataset/cdisc/ct/v48/sdtm/C106652-C106982"
        },
        {
            "alt_label": "ADL02-Usual Bowel/Bladder Function",
            "definition": "Alzheimer's Disease Cooperative Study-Activities of Daily Living Inventory, Severe Dementia Version - Regarding bowel and bladder function at the toilet, which best describes {S} usual performance during the past 4 weeks?",
            "identifier": "C106981",
            "notation": "ADL02-Usual Bowel/Bladder Function",
            "pref_label": "ADCS-ADL Severe Dementia - Usual Bowel and Bladder Function at Toilet",
            "uri": "http://id.d4k.dk/dataset/cdisc/ct/v48/sdtm/C106652-C106981"
        },
        {
            "alt_label": "ADL02-Usual Conversation Participation",
            "definition": "Alzheimer's Disease Cooperative Study-Activities of Daily Living Inventory, Severe Dementia Version - If yes, which best describes {S} usual degree of participation.",
            "identifier": "C106992",
            "notation": "ADL02-Usual Conversation Participation",
            "pref_label": "ADCS-ADL Severe Dementia - Usual Conversation Participation",
            "uri": "http://id.d4k.dk/dataset/cdisc/ct/v48/sdtm/C106652-C106992"
        },
        {
            "alt_label": "ADL02-Usual Eating Performance",
            "definition": "Alzheimer's Disease Cooperative Study-Activities of Daily Living Inventory, Severe Dementia Version - Regarding eating, which best describes {S} usual performance during the last 4 weeks?",
            "identifier": "C106979",
            "notation": "ADL02-Usual Eating Performance",
            "pref_label": "ADCS-ADL Severe Dementia - Description of Usual Performance of Eating",
            "uri": "http://id.d4k.dk/dataset/cdisc/ct/v48/sdtm/C106652-C106979"
        },
        {
            "alt_label": "ADL02-Usual Physically Dressing Perform",
            "definition": "Alzheimer's Disease Cooperative Study-Activities of Daily Living Inventory, Severe Dementia Version - Regarding physically getting dressed, which best describes {S} usual performance in the past 4 weeks?",
            "identifier": "C106984",
            "notation": "ADL02-Usual Physically Dressing Perform",
            "pref_label": "ADCS-ADL Severe Dementia - Description of Usual Performance of Physically Getting Dressed",
            "uri": "http://id.d4k.dk/dataset/cdisc/ct/v48/sdtm/C106652-C106984"
        },
        {
            "alt_label": "ADL02-Watch Television",
            "definition": "Alzheimer's Disease Cooperative Study-Activities of Daily Living Inventory, Severe Dementia Version - In the past 4 weeks, did {S} watch television?",
            "identifier": "C106987",
            "notation": "ADL02-Watch Television",
            "pref_label": "ADCS-ADL Severe Dementia - Watch Television",
            "uri": "http://id.d4k.dk/dataset/cdisc/ct/v48/sdtm/C106652-C106987"
        }
    ]
}