{
    "SKOS_CONCEPT": [
        {
            "alt_label": "APCH106A-0",
            "definition": "Acute Physiology and Chronic Health Evaluation II standardized character result for APCH106A-7.33-7.49.",
            "identifier": "C182955",
            "notation": "0",
            "pref_label": "Acute Physiology and Chronic Health Evaluation II APCH106A Standardized Character Result 0",
            "uri": "http://id.d4k.dk/dataset/cdisc/ct/v48/sdtm/C182528-C182955"
        },
        {
            "alt_label": "APCH106A-1",
            "definition": "Acute Physiology and Chronic Health Evaluation II standardized character result for APCH106A-7.5-7.59.",
            "identifier": "C182954",
            "notation": "1",
            "pref_label": "Acute Physiology and Chronic Health Evaluation II APCH106A Standardized Character Result 1",
            "uri": "http://id.d4k.dk/dataset/cdisc/ct/v48/sdtm/C182528-C182954"
        },
        {
            "alt_label": "APCH106A2",
            "definition": "Acute Physiology and Chronic Health Evaluation II standardized character result for APCH106A-7.25-7.32.",
            "identifier": "C182953",
            "notation": "2",
            "pref_label": "Acute Physiology and Chronic Health Evaluation II APCH106A Standardized Character Result 2",
            "uri": "http://id.d4k.dk/dataset/cdisc/ct/v48/sdtm/C182528-C182953"
        },
        {
            "alt_label": "APCH106A-3",
            "definition": "Acute Physiology and Chronic Health Evaluation II standardized character result for APCH106A-7.6-7.69; 7.15-7.24.",
            "identifier": "C182952",
            "notation": "3",
            "pref_label": "Acute Physiology and Chronic Health Evaluation II APCH106A Standardized Character Result 3",
            "uri": "http://id.d4k.dk/dataset/cdisc/ct/v48/sdtm/C182528-C182952"
        },
        {
            "alt_label": "APCH106A-4",
            "definition": "Acute Physiology and Chronic Health Evaluation II standardized character result for APCH106A-Greater than or equal to 7.7; Less than 7.15.",
            "identifier": "C182951",
            "notation": "4",
            "pref_label": "Acute Physiology and Chronic Health Evaluation II APCH106A Standardized Character Result 4",
            "uri": "http://id.d4k.dk/dataset/cdisc/ct/v48/sdtm/C182528-C182951"
        }
    ]
}