{
    "SKOS_CONCEPT": [
        {
            "alt_label": "",
            "definition": "The textual representation of the study intervention.",
            "identifier": "C177931",
            "notation": "Intervention Description",
            "pref_label": "Intervention Description",
            "uri": "http://id.d4k.dk/dataset/cdisc/ct/v48/protocol/C177905-C177931"
        },
        {
            "alt_label": "",
            "definition": "The identifying name for the study intervention.",
            "identifier": "C177930",
            "notation": "Intervention Name",
            "pref_label": "Intervention Name",
            "uri": "http://id.d4k.dk/dataset/cdisc/ct/v48/protocol/C177905-C177930"
        },
        {
            "alt_label": "Intervention Type",
            "definition": "The kind of product or procedure studied in a trial.",
            "identifier": "C98747",
            "notation": "Intervention Type",
            "pref_label": "Intervention Type",
            "uri": "http://id.d4k.dk/dataset/cdisc/ct/v48/protocol/C177905-C98747"
        }
    ]
}